useful_lva_sdk/__init__.py
useful_lva_sdk/client/__init__.py
useful_lva_sdk/client/lva_client.py
useful_lva_sdk/common/__init__.py
useful_lva_sdk/common/lva_pb2.py
useful_lva_sdk/common/lva_pb2_grpc.py
useful_lva_sdk/common/lva_resources_pb2.py
useful_lva_sdk/common/lva_resources_pb2_grpc.py
useful_lva_sdk/common/lva_service_pb2.py
useful_lva_sdk/common/lva_service_pb2_grpc.py
useful_lva_sdk/common/operations_pb2.py
useful_lva_sdk/common/operations_pb2_grpc.py
useful_lva_sdk/core/__init__.py
useful_lva_sdk/core/lva_graph.py
useful_lva_sdk/core/lva_graph_builder.py
useful_lva_sdk/core/operator.py
useful_lva_sdk-0.1.7.dist-info/LICENSE
useful_lva_sdk-0.1.7.dist-info/METADATA
useful_lva_sdk-0.1.7.dist-info/WHEEL
useful_lva_sdk-0.1.7.dist-info/top_level.txt
useful_lva_sdk-0.1.7.dist-info/RECORD
