Metadata-Version: 2.1
Name: useful-lva-sdk
Version: 0.1.7
Summary: Unofficial Vision AI Live Video Analytics SDK
Author: Yan Xue
Author-email: xueyan.sjtu@gmail.com
License: MIT
Classifier: Intended Audience :: Developers
Classifier: License :: OSI Approved :: MIT License
Classifier: Programming Language :: Python
Classifier: Programming Language :: Python :: 3
Classifier: Programming Language :: Python :: 3.9
Classifier: Programming Language :: Python :: 3.10
Classifier: Programming Language :: Python :: 3.11
Classifier: Operating System :: OS Independent
License-File: LICENSE
Requires-Dist: google-api-core
Requires-Dist: google-auth
Requires-Dist: googleapis-common-protos
Requires-Dist: grpcio
Requires-Dist: protobuf
